python_semantic_splitter/__init__.py
python_semantic_splitter/cli.py
python_semantic_splitter/models.py
python_semantic_splitter/parser.py
python_semantic_splitter/splitter.py
python_semantic_splitter-0.1.1.dist-info/licenses/LICENSE
python_semantic_splitter-0.1.1.dist-info/METADATA
python_semantic_splitter-0.1.1.dist-info/WHEEL
python_semantic_splitter-0.1.1.dist-info/entry_points.txt
python_semantic_splitter-0.1.1.dist-info/top_level.txt
python_semantic_splitter-0.1.1.dist-info/RECORD
