Metadata-Version: 2.4
Name: python-semantic-splitter
Version: 0.1.1
Summary: Semantic Python code splitter for AI/RAG pipelines
Home-page: https://github.com/ricky-aufvaa/python-semantic-splitter
Author: Sarabjot Singh
Author-email: Sarabjot Singh <aufvaa@gmail.com>
License: MIT
Project-URL: Homepage, https://github.com/ricky-aufvaa/python-semantic-splitter
Project-URL: Bug Reports, https://github.com/ricky-aufvaa/python-semantic-splitter/issues
Project-URL: Source, https://github.com/ricky-aufvaa/python-semantic-splitter
Project-URL: Documentation, https://github.com/ricky-aufvaa/python-semantic-splitter#readme
Keywords: python,code,splitting,semantic,parsing,ast,rag,ai,ml,chunks,nlp,text-processing
Classifier: Development Status :: 3 - Alpha
Classifier: Intended Audience :: Developers
Classifier: Topic :: Software Development :: Libraries :: Python Modules
Classifier: Topic :: Text Processing :: Linguistic
Classifier: Topic :: Scientific/Engineering :: Artificial Intelligence
Classifier: License :: OSI Approved :: MIT License
Classifier: Programming Language :: Python :: 3
Classifier: Programming Language :: Python :: 3.8
Classifier: Programming Language :: Python :: 3.9
Classifier: Programming Language :: Python :: 3.10
Classifier: Programming Language :: Python :: 3.11
Classifier: Programming Language :: Python :: 3.12
Requires-Python: >=3.8
License-File: LICENSE
Provides-Extra: yaml
Requires-Dist: PyYAML>=6.0; extra == "yaml"
Provides-Extra: dev
Requires-Dist: pytest>=7.0; extra == "dev"
Requires-Dist: pytest-cov>=4.0; extra == "dev"
Requires-Dist: black>=22.0; extra == "dev"
Requires-Dist: flake8>=5.0; extra == "dev"
Requires-Dist: mypy>=1.0; extra == "dev"
Dynamic: author
Dynamic: home-page
Dynamic: license-file
Dynamic: requires-python
